{"name":"build-javascript","namedChunkGroups":{"polyfill":{"name":"polyfill","assets":[{"name":"webpack-runtime-2b0089d2f2ebef416505.js","size":3272},{"name":"polyfill-5b319f40b2b765d17947.js","size":85842}],"filteredAssets":0,"assetsSize":89114,"filteredAuxiliaryAssets":2,"auxiliaryAssetsSize":221297},"app":{"name":"app","assets":[{"name":"webpack-runtime-2b0089d2f2ebef416505.js","size":3272},{"name":"framework-0e7066d5261223205a79.js","size":128691},{"name":"app-52684f36a5722cd09d8d.js","size":51730}],"filteredAssets":0,"assetsSize":183693,"filteredAuxiliaryAssets":3,"auxiliaryAssetsSize":547552},"component---src-pages-404-js":{"name":"component---src-pages-404-js","assets":[{"name":"component---src-pages-404-js-fe5c57a350b82e8a4a59.js","size":807}],"filteredAssets":0,"assetsSize":807,"filteredAuxiliaryAssets":1,"auxiliaryAssetsSize":1980},"component---src-pages-about-js":{"name":"component---src-pages-about-js","assets":[{"name":"component---src-pages-about-js-cbb783830be7fa6fa3e4.js","size":518}],"filteredAssets":0,"assetsSize":518,"filteredAuxiliaryAssets":1,"auxiliaryAssetsSize":869},"component---src-pages-index-js":{"name":"component---src-pages-index-js","assets":[{"name":"component---src-pages-index-js-9f46cb29eb93d93b6053.js","size":523}],"filteredAssets":0,"assetsSize":523,"filteredAuxiliaryAssets":1,"auxiliaryAssetsSize":873}},"assetsByChunkName":{"polyfill":["webpack-runtime-2b0089d2f2ebef416505.js","polyfill-5b319f40b2b765d17947.js"],"app":["webpack-runtime-2b0089d2f2ebef416505.js","framework-0e7066d5261223205a79.js","app-52684f36a5722cd09d8d.js"],"component---src-pages-404-js":["component---src-pages-404-js-fe5c57a350b82e8a4a59.js"],"component---src-pages-about-js":["component---src-pages-about-js-cbb783830be7fa6fa3e4.js"],"component---src-pages-index-js":["component---src-pages-index-js-9f46cb29eb93d93b6053.js"]},"childAssetsByChunkName":{}}