{"name":"build-javascript","namedChunkGroups":{"polyfill":{"name":"polyfill","assets":[{"name":"webpack-runtime-cbbfa4dcf863d7b0fd3c.js","size":4404},{"name":"polyfill-5b319f40b2b765d17947.js","size":85842}],"filteredAssets":0,"assetsSize":90246,"filteredAuxiliaryAssets":2,"auxiliaryAssetsSize":225632},"app":{"name":"app","assets":[{"name":"webpack-runtime-cbbfa4dcf863d7b0fd3c.js","size":4404},{"name":"framework-0e7066d5261223205a79.js","size":128691},{"name":"app-ecd602aa9d6bf70a5c9e.js","size":51778}],"filteredAssets":0,"assetsSize":184873,"filteredAuxiliaryAssets":3,"auxiliaryAssetsSize":551887},"component---src-pages-404-js":{"name":"component---src-pages-404-js","assets":[{"name":"component---src-pages-404-js-fe5c57a350b82e8a4a59.js","size":807}],"filteredAssets":0,"assetsSize":807,"filteredAuxiliaryAssets":1,"auxiliaryAssetsSize":1980},"component---src-pages-about-js":{"name":"component---src-pages-about-js","assets":[{"name":"styles.c5eeb118fa884f56d3cb.css","size":307},{"name":"component---src-pages-about-js-7337a72f72e97384d741.js","size":1081}],"filteredAssets":0,"assetsSize":1388,"filteredAuxiliaryAssets":1,"auxiliaryAssetsSize":2316},"component---src-pages-index-js":{"name":"component---src-pages-index-js","assets":[{"name":"styles.c5eeb118fa884f56d3cb.css","size":307},{"name":"component---src-pages-index-js-b888bc477b511b274e7f.js","size":1059}],"filteredAssets":0,"assetsSize":1366,"filteredAuxiliaryAssets":1,"auxiliaryAssetsSize":2294}},"assetsByChunkName":{"polyfill":["webpack-runtime-cbbfa4dcf863d7b0fd3c.js","polyfill-5b319f40b2b765d17947.js"],"app":["webpack-runtime-cbbfa4dcf863d7b0fd3c.js","framework-0e7066d5261223205a79.js","app-ecd602aa9d6bf70a5c9e.js"],"component---src-pages-404-js":["component---src-pages-404-js-fe5c57a350b82e8a4a59.js"],"component---src-pages-about-js":["styles.c5eeb118fa884f56d3cb.css","component---src-pages-about-js-7337a72f72e97384d741.js"],"component---src-pages-index-js":["styles.c5eeb118fa884f56d3cb.css","component---src-pages-index-js-b888bc477b511b274e7f.js"]},"childAssetsByChunkName":{}}